mediafile.py
moe_mediafile-0.10.1.dist-info/LICENSE
moe_mediafile-0.10.1.dist-info/WHEEL
moe_mediafile-0.10.1.dist-info/METADATA
moe_mediafile-0.10.1.dist-info/RECORD
