Metadata-Version: 2.1
Name: moe_mediafile
Version: 0.10.1
Summary: elegant audio file tagging
Author-email: Adrian Sampson <adrian@radbox.org>, Jacob Pavlock <jtpavlock@gmail.com>
Requires-Python: >=3.7
Classifier: Topic :: Multimedia :: Sound/Audio
Classifier: License :: OSI Approved :: MIT License
Classifier: Environment :: Web Environment
Classifier: Programming Language :: Python :: 3.7
Classifier: Programming Language :: Python :: 3.8
Classifier: Programming Language :: Python :: 3.9
Classifier: Programming Language :: Python :: 3.10
Classifier: Programming Language :: Python :: Implementation :: PyPy
Requires-Dist: six>=1.9
Requires-Dist: mutagen>=1.46
